mysent/__init__.py
mysent-0.1.0.dist-info/METADATA
mysent-0.1.0.dist-info/WHEEL
mysent-0.1.0.dist-info/RECORD
