Metadata-Version: 2.1
Name: mysent
Version: 0.1.0
Summary: Toolset to describe and embedding schemes of editable messages to the code
License: GNU GPLv3
Author: Mikhail Hakobyan
Author-email: ns-tonic@yandex.ru
Requires-Python: >=3.10,<4.0
Classifier: License :: Other/Proprietary License
Classifier: Programming Language :: Python :: 3
Classifier: Programming Language :: Python :: 3.10
Classifier: Programming Language :: Python :: 3.11
Classifier: Programming Language :: Python :: 3.12
